MANIFEST.in
README.md
setup.py
pyGEDI/__init__.py
pyGEDI.egg-info/PKG-INFO
pyGEDI.egg-info/SOURCES.txt
pyGEDI.egg-info/dependency_links.txt
pyGEDI.egg-info/top_level.txt