Metadata-Version: 1.0
Name: pyGEDI
Version: 0.2.5
Summary: pyGED is a Python Package for NASA Global Ecosystem Dynamics Investigation (GEDI) mission data extraction, analysis, processing and visualization.
Home-page: https://github.com/EduinHSERNA/pyGEDI
Author: EduinHSERNA
Author-email: UNKNOWN
License: UNKNOWN
Keywords: GEDI
Platform: UNKNOWN
